[
  {
    "name": "Aloha Table Tennis Association",
    "id": "aloha-tta",
    "location": "Honolulu",
    "type": "Training Center",
    "tags": "Good for Practice Matches,Good for Training,League Play,Casual Play,Coaching Available",
    "pricePerDay": "$10",
    "priceBy": "person",
    "address": "1375 Dillingham Blvd #204\nHonolulu, HI 96817",
    "website": "https://alohatabletennis.org/",
    "notes": "We made it to Honolulu! This club was a bit tricky to find - it's located on the second floor in the back of a mixed use building. There are signs hanging on the walkway above the hardware store, visible from the parking lot. Check out Bob's BBQ across the street for a quick bite before practice.\n\nEveryone at the club was cheerful and welcoming (as Hawaiians tend to be!). We played some singles as well as a round of 44mm-short-pips doubles (yikes) with the local players, who seemed to mostly range from beginner to ~2000 USATT, depending on the day. \n\nThere's no AC, so bring a towel! There is a fridge full of cold beverages and free snacks, though. The flooring was great, ceiling height was acceptable, space was good, tables were high quality. They seem to have an active league with solid attendance as well.\n\nMahalo especially to Billy and Diane for making us feel at home. Hopefully next time we can stay a bit longer... and until next time, aloha!",
    "attachments": "1569265929810.jpg (https://dl.airtable.com/.attachments/9d121cc7c622db8ee7779f7d54098603/5347ce3f/1569265929810.jpg),1569265865559.jpg (https://dl.airtable.com/.attachments/a2265acdb00af8a76dcc6b680b44d74d/3a5b528b/1569265865559.jpg)",
    "googlePlaceId": "ChIJKz6POY1uAHwRvsQl__UOGoI",
    "lastModified": "5/30/2021 11:26pm",
    "lat": 21.324112832759834,
    "lng": -157.87545725818782,
    "traits": {
      "_permanence": 2,
      "_hours": 2,
      "_ceiling_height": 1,
      "_flooring": 2,
      "_lighting": 2,
      "_court_size": 1,
      "_barriers": 2,
      "_group_training": 0,
      "_walkin_friendly": 2,
      "_pro_coaches": null,
      "_tournaments": null,
      "_table_quality": 2,
      "_climate_control": 1,
      "_accessibility": 0
    }
  },
  {
    "name": "Maui Table Tennis",
    "location": "Maui",
    "type": "No Permanent Location,Multipurpose Space",
    "tags": "Casual Play,Good for Practice Matches",
    "pricePerDay": "$5",
    "website": "https://mauitabletennis.webs.com/",
    "notes": "",
    "attachments": "1569266005384.jpg (https://dl.airtable.com/.attachments/58d71f8ab8e45999d51bb87559457249/744def84/1569266005384.jpg),1569266374386.jpg (https://dl.airtable.com/.attachments/0254a77f4e0b44122eee3f2273699ead/8a5d024a/1569266374386.jpg),1569266294302.jpg (https://dl.airtable.com/.attachments/7bf08b47360e65b15a45787931420cdd/07451cda/1569266294302.jpg),1569266170069.jpg (https://dl.airtable.com/.attachments/3f303cb8c370319daa1af022304c2a4e/47e6074f/1569266170069.jpg)",
    "lastModified": "9/23/2019 3:57pm",
    "traits": {
      "_permanence": 0,
      "_hours": null,
      "_ceiling_height": null,
      "_flooring": 0,
      "_lighting": null,
      "_court_size": null,
      "_barriers": null,
      "_group_training": 0,
      "_walkin_friendly": 2,
      "_pro_coaches": 0,
      "_tournaments": 0,
      "_table_quality": null,
      "_climate_control": null,
      "_accessibility": null
    },
    "locations": [
      {
        "name": "Maui Table Tennis - Lahaina",
        "id": "maui-ttc-lahaina",
        "address": "Lahaina Civic Center Gymnasium \n1840 Honoapiilani Highway, Lahaina",
        "lat": 20.90538244408989,
        "lng": -156.6836089544872,
        "visited": false
      },
      {
        "name": "Maui Table Tennis - Makawao",
        "id": "maui-ttc-makawao",
        "address": "Eddie Tam Gymnasium\n931 Makawao Avenue, Makawao",
        "lat": 20.850685524876113,
        "lng": -156.31617270725553
      },
      {
        "name": "Maui Table Tennis - Kahului",
        "id": "maui-ttc-kahului",
        "address": "Kahului Community Center (Annex)\n268 Uhu Street, Kahului",
        "lat": 20.879753074618346,
        "lng": -156.47732433121254,
        "visited": true
      }
    ]
  },
  {
    "name": "Table Tennis & More",
    "id": "ttm-hawaii",
    "address": "Kohala Civic Center\n54-3900 Akoni Pule Hwy\nKapaau, HI 96755",
    "pricePerDay": "$0",
    "website": "http://www.tabletennisandmore.com/hawittc.htm",
    "facebook": "https://www.facebook.com/NKTTC/",
    "lat": 20.23015237730058,
    "lng": -155.79814541612615,
    "traits": {
      "_permanence": 0,
      "_hours": 1,
      "_ceiling_height": 0,
      "_flooring": 0,
      "_lighting": 2,
      "_court_size": 0,
      "_barriers": 0,
      "_group_training": 0,
      "_walkin_friendly": 2,
      "_pro_coaches": 0,
      "_tournaments": 0,
      "_table_quality": 1,
      "_climate_control": 2,
      "_accessibility": null
    }
  },
  {
    "name": "Waimea Table Tennis Club",
    "id": "waimea-ttc",
    "address": "65-1260 Kawaihae Rd, Waimea, HI 96743",
    "pricePerDay": "$0",
    "website": "http://www.tabletennisandmore.com/waimeattc.htm",
    "facebook": "https://www.facebook.com/waimeatt/",
    "phone": "808-345-8443",
    "lat": 20.022782313280523,
    "lng": -155.6726508468141,
    "traits": {
      "_permanence": 0,
      "_hours": 1,
      "_ceiling_height": 2,
      "_flooring": 0,
      "_lighting": 1,
      "_court_size": 0,
      "_barriers": 1,
      "_group_training": 0,
      "_walkin_friendly": 2,
      "_pro_coaches": 0,
      "_tournaments": 0,
      "_table_quality": 1,
      "_climate_control": null,
      "_accessibility": null
    }
  },
  {
    "name": "Captain Cook Table Tennis Club",
    "id": "captain-cook-ttc-kona",
    "address": "Yano Hall, 82-6156 Mamalahoa Highway, Captain Cook, HI 96740",
    "website": "http://www.tabletennisandmore.com/captaincookclub.htm",
    "facebook": "https://www.facebook.com/tabletennishawaii/",
    "pricePerDay": "$0",
    "lat": 19.489435267945,
    "lng": -155.91051588730232,
    "traits": {
      "_permanence": 0,
      "_hours": 0,
      "_ceiling_height": 1,
      "_flooring": 0,
      "_lighting": 1,
      "_club_size": 0,
      "_court_size": 0,
      "_barriers": 1,
      "_group_training": 0,
      "_walkin_friendly": 2,
      "_pro_coaches": 0,
      "_tournaments": 0,
      "_table_quality": 1,
      "_climate_control": null,
      "_accessibility": null
    }
  },
  {
    "name": "Kona Table Tennis Club",
    "id": "kona-ttc",
    "address": "Kekuaokalani Gymnasium, 75-5500 Kuakini Hwy",
    "website": "https://konapong.wixsite.com/kttc",
    "pricePerDay": "$0",
    "lat": 19.640985837434336,
    "lng": -156.00211952777997,
    "traits": {
      "_permanence": 0,
      "_hours": 0,
      "_ceiling_height": 0,
      "_flooring": 0,
      "_lighting": 1,
      "_club_size": 0,
      "_court_size": 0,
      "_barriers": 0,
      "_group_training": 0,
      "_walkin_friendly": 2,
      "_pro_coaches": 0,
      "_tournaments": 0,
      "_table_quality": 1,
      "_climate_control": null,
      "_accessibility": null
    }
  },
  {
    "name": "Big Island Table Tennis Association",
    "id": "big-island-tta",
    "pricePerDay": "$5",
    "website": "http://bitta.org/",
    "facebook": "https://www.facebook.com/join.bitta/",
    "address": "Island of Hawaii YMCA, 300 W Lanikaula St, Hilo, HI 96720",
    "lat": 19.7049808,
    "lng": -155.0799355206924,
    "images": [
      "http://bitta.org/sites/default/files/TT%20Nov%202015%20Tourney%20Kids%20and%20Women-05882.jpg"
    ],
    "traits": {
      "_permanence": 0,
      "_hours": 1,
      "_ceiling_height": 2,
      "_flooring": 0,
      "_lighting": 2,
      "_club_size": 0,
      "_court_size": 1,
      "_barriers": 1,
      "_group_training": 0,
      "_walkin_friendly": 2,
      "_pro_coaches": 0,
      "_tournaments": 0,
      "_table_quality": 1,
      "_climate_control": null,
      "_accessibility": null
    }
  },
  {
    "name": "Beretania District Park",
    "id": "beretania-district-park",
    "address": "Beretania District Park, 1290 Aala St",
    "lat": 21.320030389601843,
    "lng": -157.86233739648122,
    "pricePerDay": "$0",
    "traits": {
      "_permanence": 0,
      "_hours": 2,
      "_ceiling_height": null,
      "_flooring": null,
      "_lighting": null,
      "_club_size": null,
      "_court_size": null,
      "_barriers": null,
      "_group_training": null,
      "_walkin_friendly": 1,
      "_pro_coaches": null,
      "_tournaments": null,
      "_table_quality": null,
      "_climate_control": null,
      "_accessibility": null
    }
  },
  {
    "name": "The Honolulu Club",
    "id": "honolulu-club",
    "website": "https://www.honoluluclub.com/",
    "address": "932 Ward Avenue, 7th Floor, Honolulu, HI 96814",
    "lat": 21.302015181692738,
    "lng": -157.85090254494372,
    "pricePerDay": "$25",
    "phone": "808-688-3356",
    "traits": {
      "_permanence": 0,
      "_hours": 0,
      "_ceiling_height": null,
      "_flooring": null,
      "_lighting": null,
      "_club_size": null,
      "_court_size": null,
      "_barriers": null,
      "_group_training": null,
      "_walkin_friendly": 1,
      "_pro_coaches": null,
      "_tournaments": null,
      "_table_quality": null,
      "_climate_control": null,
      "_accessibility": null
    }
  },
  {
    "name": "Kilauea Gym",
    "id": "kilauea-gym",
    "address": "Kilauea Gym, 4109 Kilauea Ave",
    "lat": 21.269467650416047,
    "lng": -157.79501311280106,
    "pricePerDay": "$0",
    "phone": "(808) 733-7356",
    "traits": {
      "_permanence": 0,
      "_hours": 1,
      "_ceiling_height": null,
      "_flooring": null,
      "_lighting": null,
      "_club_size": null,
      "_court_size": null,
      "_barriers": null,
      "_group_training": null,
      "_walkin_friendly": 1,
      "_pro_coaches": null,
      "_tournaments": null,
      "_table_quality": null,
      "_climate_control": null,
      "_accessibility": null
    }
  },
  {
    "name": "Manoa District Park",
    "id": "manoa-district-park",
    "address": "Manoa District Park, room off side of main gym, 2721 Kaaipu Ave",
    "lat": 21.31705737577409,
    "lng": -157.8079623231961,
    "pricePerDay": "$0",
    "phone": "(808) 988-0513",
    "traits": {
      "_permanence": 0,
      "_hours": 0,
      "_ceiling_height": null,
      "_flooring": null,
      "_lighting": null,
      "_club_size": null,
      "_court_size": null,
      "_barriers": null,
      "_group_training": null,
      "_walkin_friendly": 1,
      "_pro_coaches": null,
      "_tournaments": null,
      "_table_quality": null,
      "_climate_control": null,
      "_accessibility": null
    }
  },
  {
    "name": "Newtown Rec Center",
    "id": "newtown-rec-center",
    "address": "98-456 Kaahele St",
    "lat": 21.39823098197438,
    "lng": -157.94745114494208,
    "pricePerDay": "$3",
    "phone": "(808) 728-7927",
    "traits": {
      "_permanence": 0,
      "_hours": 0,
      "_ceiling_height": null,
      "_flooring": null,
      "_lighting": null,
      "_club_size": null,
      "_court_size": null,
      "_barriers": null,
      "_group_training": null,
      "_walkin_friendly": 1,
      "_pro_coaches": null,
      "_tournaments": null,
      "_table_quality": null,
      "_climate_control": null,
      "_accessibility": null
    }
  },
  {
    "name": "Waipahu District Park",
    "id": "waipahu-district",
    "address": "94-230 Paiwa St, Waipahu, HI 96797",
    "lat": 21.38745767599195,
    "lng": -157.99912572960014,
    "pricePerDay": "$0",
    "phone": "(808) 675-7129",
    "traits": {
      "_permanence": 0,
      "_hours": 1,
      "_ceiling_height": null,
      "_flooring": null,
      "_lighting": null,
      "_club_size": null,
      "_court_size": null,
      "_barriers": null,
      "_group_training": null,
      "_walkin_friendly": 1,
      "_pro_coaches": null,
      "_tournaments": null,
      "_table_quality": null,
      "_climate_control": null,
      "_accessibility": null
    }
  },
  {
    "name": "Waikiki Community Center",
    "id": "waikiki-community-center",
    "address": "310 Paoakalani Ave, Honolulu, HI 96815",
    "lat": 21.275444750415403,
    "lng": -157.82019084309533,
    "pricePerDay": "$5",
    "phone": "(808) 923-1802",
    "traits": {
      "_permanence": 0,
      "_hours": 0,
      "_ceiling_height": null,
      "_flooring": null,
      "_lighting": null,
      "_club_size": null,
      "_court_size": null,
      "_barriers": null,
      "_group_training": null,
      "_walkin_friendly": 1,
      "_pro_coaches": null,
      "_tournaments": null,
      "_table_quality": null,
      "_climate_control": null,
      "_accessibility": null
    }
  },
  {
    "name": "Lanai Gym",
    "id": "lanai-gym",
    "address": "717 Fraser Ave, Lanai City, HI 96763",
    "lat": 20.825066288840084,
    "lng": -156.92194450262303,
    "phone": "(808) 565-6979",
    "traits": {
      "_permanence": 0,
      "_hours": 0,
      "_ceiling_height": null,
      "_flooring": null,
      "_lighting": null,
      "_club_size": null,
      "_court_size": null,
      "_barriers": null,
      "_group_training": null,
      "_walkin_friendly": 1,
      "_pro_coaches": null,
      "_tournaments": null,
      "_table_quality": null,
      "_climate_control": null,
      "_accessibility": null
    }
  }
]
